{
  "main": {
    "id": "c1ee576258cf01af",
    "type": "split",
    "children": [
      {
        "id": "3f4661c028df3a9c",
        "type": "tabs",
        "children": [
          {
            "id": "c70e824ea1db4b59",
            "type": "leaf",
            "state": {
              "type": "markdown",
              "state": {
                "file": "Linux/Linux 05 권한 관리 명령어.md",
                "mode": "source",
                "source": false
              }
            }
          },
          {
            "id": "a4d9d75ccbebacb2",
            "type": "leaf",
            "state": {
              "type": "markdown",
              "state": {
                "file": "Linux/Linux 06.md",
                "mode": "source",
                "source": false
              }
            }
          }
        ],
        "currentTab": 1
      }
    ],
    "direction": "vertical"
  },
  "left": {
    "id": "f170aa08c630400f",
    "type": "split",
    "children": [
      {
        "id": "8e738057bf55eb21",
        "type": "tabs",
        "children": [
          {
            "id": "da9dbe85c624316b",
            "type": "leaf",
            "state": {
              "type": "file-explorer",
              "state": {
                "sortOrder": "alphabetical"
              }
            }
          },
          {
            "id": "d8e262d331188cde",
            "type": "leaf",
            "state": {
              "type": "search",
              "state": {
                "query": "",
                "matchingCase": false,
                "explainSearch": false,
                "collapseAll": false,
                "extraContext": false,
                "sortOrder": "alphabetical"
              }
            }
          },
          {
            "id": "c288d886998b7b26",
            "type": "leaf",
            "state": {
              "type": "bookmarks",
              "state": {}
            }
          }
        ]
      }
    ],
    "direction": "horizontal",
    "width": 272.5
  },
  "right": {
    "id": "f3619a3373a31fa6",
    "type": "split",
    "children": [
      {
        "id": "9bbffc973594ec74",
        "type": "tabs",
        "children": [
          {
            "id": "ad97b60a6b66a07e",
            "type": "leaf",
            "state": {
              "type": "backlink",
              "state": {
                "file": "Linux/Linux 06.md",
                "collapseAll": false,
                "extraContext": false,
                "sortOrder": "alphabetical",
                "showSearch": false,
                "searchQuery": "",
                "backlinkCollapsed": false,
                "unlinkedCollapsed": true
              }
            }
          },
          {
            "id": "34c3739921a2799d",
            "type": "leaf",
            "state": {
              "type": "outgoing-link",
              "state": {
                "file": "Linux/Linux 06.md",
                "linksCollapsed": false,
                "unlinkedCollapsed": true
              }
            }
          },
          {
            "id": "037c2c0d911daa49",
            "type": "leaf",
            "state": {
              "type": "tag",
              "state": {
                "sortOrder": "frequency",
                "useHierarchy": true
              }
            }
          },
          {
            "id": "cfce0f21f8b39802",
            "type": "leaf",
            "state": {
              "type": "outline",
              "state": {
                "file": "Linux/Linux 06.md"
              }
            }
          }
        ],
        "currentTab": 3
      }
    ],
    "direction": "horizontal",
    "width": 300,
    "collapsed": true
  },
  "left-ribbon": {
    "hiddenItems": {
      "switcher:퀵 스위처 열기": false,
      "graph:그래프 뷰 열기": false,
      "canvas:새 캔버스 만들기": false,
      "daily-notes:오늘의 데일리 노트 열기": false,
      "templates:템플릿 삽입": false,
      "command-palette:명령어 팔레트 열기": false,
      "obsidian-projects:Open projects": false,
      "obsidian-excalidraw-plugin:Create new drawing": false
    }
  },
  "active": "a4d9d75ccbebacb2",
  "lastOpenFiles": [
    "Linux/Linux 05 권한 관리 명령어.md",
    "Linux/Linux 06.md",
    "ProgrammingLanguage/C/포인터와 배열, 포인터 연산.md",
    "Linux/Linux 03 기본 명령어.md",
    "Linux/Linux 02 vm의 네트워크 환경.md",
    "Linux/Linux 01 Linux와 개발 환경.md",
    "Linux/Linux 04 파일 시스템 명령어.md",
    "Web/네트워크 톺아보기.md",
    "Web/IP.md",
    "Web/개발 환경을 위한 네트워크 설정(VMware).md",
    "Web/NAT.md",
    "Web/WAS와 Web Server.md",
    "Web/REST.md",
    "Web/README.md",
    "Web/브라우저의 동작(백엔드).md",
    "1. Books/README.md",
    "1. Books/Clean Code.md",
    "README.md",
    "Linux/README.md",
    "Linux/Exit code.md",
    "Linux/Zsh, Oh-My-Zsh.md",
    "Linux/심볼릭 링크, 하드 링크.md",
    "2. Conference/토스ㅣSLASH 22 - 지속 성장 가능한 코드를 만들어가는 방법.md",
    "Algorithm/Binary Searh.md",
    "Algorithm/Hash Table.md",
    "Algorithm/Hash Map - 내부 작동.md",
    "무제 파일.canvas",
    "Linux",
    "ProgrammingLanguage/Java/Basic",
    "_posts/03-2. network",
    "_posts",
    "Framework/Spring",
    "Framework",
    "ProgrammingLanguage/Python",
    "ProgrammingLanguage/C",
    "ProgrammingLanguage/Java",
    "DataBase/SQLD",
    "4 - 5. DataBase/Images/Tt7.png",
    "Pasted image 20240115001403 1 1.png",
    "Pasted image 20240115011439 1 1.png",
    "Pasted image 20240115011104 1 1.png",
    "Pasted image 20240115010854 1 1.png",
    "Pasted image 20240115005935 1 1.png",
    "Pasted image 20240115005053 1 1.png",
    "Pasted image 20240115010212.png",
    "Pasted image 20240115010248.png",
    "Pasted image 20240115010333.png"
  ]
}